[
    {
      "songname": "Death_Bed",
      "artistname": "Powfu",
    "language":"english"
    
    },
    {
      "songname": "Bad_Liar",
      "artistname": "Imagine_Dragons",
       "language":"english"
     
    },
    {
      "songname": "Faded",
      "artistname": "Alan_Walker",
      "language":"english"
    },
    {
      "songname": "Hate_Me",
      "artistname": "Ellie_Goulding",
     "language":"english"
    },
    {
      "songname": "Solo",
      "artistname": "Clean_Bandit",
      "language":"english"
    
    },
    {
      "songname": "Without_Me",
      "artistname": "Halsey",
     "language":"english"
    },
    {
      "songname": "dance monkey",
      "artistname": "tones and i",
       "language":"english"
     
    },
    {
      "songname": "girls like you",
      "artistname": "maroon 5",
       "language":"english"
     
    },
    {
      "songname": "paint the town red",
      "artistname": "doja cat",
       "language":"english"
     
    },
    {
      "songname": "old town road",
      "artistname": "lil nas x",
       "language":"english"
     
    },
    {
      "songname": "o mahi",
      "artistname": "arijit singh",
       "language":"hindi"
     
    },
    {
      "songname": "apna bana le",
      "artistname": "arijit singh",
       "language":"hindi"
     
    },
    {
      "songname": "quafirana",
      "artistname": "arijit singh",
       "language":"hindi"
     
    },
    {
      "songname": "pee loon",
      "artistname": "mohit chauhan",
       "language":"hindi"
     
    },
    {
      "songname": "kun faya kun",
      "artistname": "mohit chauhan",
       "language":"hindi"
     
    },
    {
      "songname": "king shit",
      "artistname": "shubh",
       "language":"punjabi"
     
    },
    {
      "songname": "3 peg",
      "artistname": "sharry mann",
       "language":"punjabi"
     
    },
    {
      "songname": "softly",
      "artistname": "ikky",
       "language":"punjabi"
     
    },
    {
      "songname": "with you",
      "artistname": "ap dhillon",
       "language":"punjabi"
     
    },
    {
      "songname": "backbone",
      "artistname": "harrdy sandhu",
       "language":"punjabi"
     
    },
    {
      "songname": "na ja",
      "artistname": "pav dharia",
       "language":"punjabi"
     
    },
    {
      "songname": "one love",
      "artistname": "shubh",
       "language":"punjabi"
     
    },
    {
      "songname": "295",
      "artistname": "sidhu moose wala",
       "language":"punjabi"
     
    },
    {
      "songname": "yeh baby",
      "artistname": "garry sandhu",
       "language":"punjabi"
     
    },
    {
      "songname": "minna minna",
      "artistname": "garry sandhu",
       "language":"punjabi"
     
    }
    


  ]